typosquatting/__init__.py
typosquatting/typosquatting.py
typosquatting-0.9.dist-info/METADATA
typosquatting-0.9.dist-info/WHEEL
typosquatting-0.9.dist-info/top_level.txt
typosquatting-0.9.dist-info/RECORD
